activemodel/__init__.py
activemodel/base_model.py
activemodel/celery.py
activemodel/errors.py
activemodel/logger.py
activemodel/query_wrapper.py
activemodel/session_manager.py
activemodel/utils.py
activemodel/cli/__init__.py
activemodel/mixins/__init__.py
activemodel/mixins/pydantic_json.py
activemodel/mixins/soft_delete.py
activemodel/mixins/timestamps.py
activemodel/mixins/typeid.py
activemodel/patches/__init__.py
activemodel/patches/get_column_from_field_patch.py
activemodel/pytest/__init__.py
activemodel/pytest/factories.py
activemodel/pytest/plugin.py
activemodel/pytest/transaction.py
activemodel/pytest/truncate.py
activemodel/types/__init__.py
activemodel/types/sqlalchemy_protocol.py
activemodel/types/sqlalchemy_protocol.pyi
activemodel/types/typeid.py
activemodel/types/typeid_patch.py
activemodel-0.14.1.dist-info/METADATA
activemodel-0.14.1.dist-info/WHEEL
activemodel-0.14.1.dist-info/entry_points.txt
activemodel-0.14.1.dist-info/licenses/LICENSE
activemodel-0.14.1.dist-info/RECORD
