Metadata-Version: 2.4
Name: activemodel
Version: 0.14.1
Summary: Make SQLModel more like an a real ORM
Project-URL: Repository, https://github.com/iloveitaly/activemodel
Author-email: Michael Bianco <iloveitaly@gmail.com>
License-File: LICENSE
Keywords: activemodel,activerecord,orm,sqlalchemy,sqlmodel
Requires-Python: >=3.12
Requires-Dist: python-decouple-typed>=3.11.0
Requires-Dist: sqlmodel>=0.0.27
Requires-Dist: textcase>=0.4.0
Requires-Dist: typeid-python==0.3.3
